discord_voice/__init__.py
discord_voice/ctx.py
discord_voice/embed.py
discord_voice_text-0.0.9.dist-info/METADATA
discord_voice_text-0.0.9.dist-info/WHEEL
discord_voice_text-0.0.9.dist-info/top_level.txt
discord_voice_text-0.0.9.dist-info/RECORD
